{
    "meta": {
        "num_tuples": 7919,
        "num_attributes": 9,
        "num_attributes_in_BN": 8,
        "all_attributes": [
            "Attendance ID",
            "Hospital",
            "Time in A&E (mins)",
            "Treatment",
            "Gender",
            "Index of Multiple Deprivation Decile",
            "Arrival Date",
            "Arrival hour range",
            "Age bracket"
        ],
        "candidate_keys": [
            "Attendance ID"
        ],
        "non_categorical_string_attributes": [
            "Attendance ID"
        ],
        "attributes_in_BN": [
            "Arrival Date",
            "Gender",
            "Treatment",
            "Time in A&E (mins)",
            "Arrival hour range",
            "Age bracket",
            "Index of Multiple Deprivation Decile",
            "Hospital"
        ]
    },
    "attribute_description": {
        "Attendance ID": {
            "name": "Attendance ID",
            "data_type": "String",
            "is_categorical": false,
            "is_candidate_key": true,
            "min": 7,
            "max": 10,
            "missing_rate": 0.0,
            "distribution_bins": [
                7,
                10
            ],
            "distribution_probabilities": [
                0,
                0
            ]
        },
        "Hospital": {
            "name": "Hospital",
            "data_type": "String",
            "is_categorical": true,
            "is_candidate_key": false,
            "min": 1,
            "max": 2,
            "missing_rate": 0.0,
            "distribution_bins": [
                1,
                6,
                23,
                7,
                14,
                25,
                9,
                20,
                3,
                24,
                8,
                12,
                21,
                26,
                15,
                10,
                11,
                2,
                19,
                17,
                16,
                5,
                4,
                13,
                22,
                18
            ],
            "distribution_probabilities": [
                0,
                0,
                0,
                0,
                0,
                0,
                0,
                0,
                0,
                0,
                0,
                0,
                0,
                0,
                0,
                0,
                0,
                0,
                0,
                0,
                0,
                0,
                0,
                0,
                0,
                0
            ]
        },
        "Time in A&E (mins)": {
            "name": "Time in A&E (mins)",
            "data_type": "Integer",
            "is_categorical": false,
            "is_candidate_key": false,
            "min": 1,
            "max": 421,
            "missing_rate": 0.0,
            "distribution_bins": [
                1.0,
                421.0
            ],
            "distribution_probabilities": [
                0.5,
                0.5
            ]
        },
        "Treatment": {
            "name": "Treatment",
            "data_type": "String",
            "is_categorical": true,
            "is_candidate_key": false,
            "min": 3,
            "max": 44,
            "missing_rate": 0.0,
            "distribution_bins": [
                "None (consider guidance/advice option)",
                "Plaster of Paris",
                "Occupational Therapy",
                "Resuscitation/cardiopulmonary resuscitation",
                "Dressing/wound review",
                "Infusion fluids",
                "Other (consider alternatives)",
                "Social work intervention",
                "Oral airway",
                "Physiotherapy",
                "Joint aspiration",
                "Dental treatment",
                "Minor surgery",
                "Bandage/support",
                "Blood product transfusion",
                "Chest drain",
                "Dressing",
                "Nasal airway",
                "Burns review",
                "Nebuliser/spacer",
                "Central line",
                "Recording vital signs",
                "Fracture review",
                "Sutures",
                "Lumbar puncture",
                "Wound closure (excluding sutures)",
                "Defibrillation/pacing",
                "Sling/collar cuff/broad arm sling",
                "Splint",
                "Wound cleaning",
                "Anaesthesia",
                "Arterial line",
                "Incision & drainage",
                "Removal foreign body",
                "Urinary catheter/suprapubic",
                "Guidance/advice only",
                "Tetanus",
                "Eye",
                "Prescription/medicines prepared to take away"
            ],
            "distribution_probabilities": [
                0.02564102564102564,
                0.02564102564102564,
                0.02564102564102564,
                0.02564102564102564,
                0.02564102564102564,
                0.02564102564102564,
                0.02564102564102564,
                0.02564102564102564,
                0.02564102564102564,
                0.02564102564102564,
                0.02564102564102564,
                0.02564102564102564,
                0.02564102564102564,
                0.02564102564102564,
                0.02564102564102564,
                0.02564102564102564,
                0.02564102564102564,
                0.02564102564102564,
                0.02564102564102564,
                0.02564102564102564,
                0.02564102564102564,
                0.02564102564102564,
                0.02564102564102564,
                0.02564102564102564,
                0.02564102564102564,
                0.02564102564102564,
                0.02564102564102564,
                0.02564102564102564,
                0.02564102564102564,
                0.02564102564102564,
                0.02564102564102564,
                0.02564102564102564,
                0.02564102564102564,
                0.02564102564102564,
                0.02564102564102564,
                0.02564102564102564,
                0.02564102564102564,
                0.02564102564102564,
                0.02564102564102564
            ]
        },
        "Gender": {
            "name": "Gender",
            "data_type": "String",
            "is_categorical": true,
            "is_candidate_key": false,
            "min": 4,
            "max": 6,
            "missing_rate": 0.0,
            "distribution_bins": [
                "Female",
                "Male"
            ],
            "distribution_probabilities": [
                0.5,
                0.5
            ]
        },
        "Index of Multiple Deprivation Decile": {
            "name": "Index of Multiple Deprivation Decile",
            "data_type": "Integer",
            "is_categorical": false,
            "is_candidate_key": false,
            "min": 1,
            "max": 10,
            "missing_rate": 0.0,
            "distribution_bins": [
                1.0,
                10.0
            ],
            "distribution_probabilities": [
                0.5,
                0.5
            ]
        },
        "Arrival Date": {
            "name": "Arrival Date",
            "data_type": "String",
            "is_categorical": true,
            "is_candidate_key": false,
            "min": 10,
            "max": 10,
            "missing_rate": 0.0,
            "distribution_bins": [
                "2019-04-06",
                "2019-04-02",
                "2019-04-01",
                "2019-04-04",
                "2019-04-05",
                "2019-04-03"
            ],
            "distribution_probabilities": [
                0.16666666666666666,
                0.16666666666666666,
                0.16666666666666666,
                0.16666666666666666,
                0.16666666666666666,
                0.16666666666666666
            ]
        },
        "Arrival hour range": {
            "name": "Arrival hour range",
            "data_type": "String",
            "is_categorical": true,
            "is_candidate_key": false,
            "min": 5,
            "max": 5,
            "missing_rate": 0.0,
            "distribution_bins": [
                "08-11",
                "16-19",
                "04-07",
                "00-03",
                "20-23",
                "12-15"
            ],
            "distribution_probabilities": [
                0.16666666666666666,
                0.16666666666666666,
                0.16666666666666666,
                0.16666666666666666,
                0.16666666666666666,
                0.16666666666666666
            ]
        },
        "Age bracket": {
            "name": "Age bracket",
            "data_type": "String",
            "is_categorical": true,
            "is_candidate_key": false,
            "min": 3,
            "max": 5,
            "missing_rate": 0.0,
            "distribution_bins": [
                "18-24",
                "45-64",
                "0-17",
                "25-44",
                "65-84",
                "85-"
            ],
            "distribution_probabilities": [
                0.16666666666666666,
                0.16666666666666666,
                0.16666666666666666,
                0.16666666666666666,
                0.16666666666666666,
                0.16666666666666666
            ]
        }
    }
}